e5py/__init__.py
e5py/__main__.py
e5py/blockdata.py
e5py/cfg.py
e5py/colorscheme.py
e5py/constants.py
e5py/dbs.py
e5py/e5.py
e5py/e5_widgets.py
e5py/ini.py
e5py/main.kv
e5py/main.py
e5py/misc.py
e5py/speed_tests.py
e5-1.3.25.dist-info/LICENSE
e5-1.3.25.dist-info/METADATA
e5-1.3.25.dist-info/WHEEL
e5-1.3.25.dist-info/top_level.txt
e5-1.3.25.dist-info/RECORD
