Metadata-Version: 2.2
Name: e5
Version: 1.3.25
Summary: Configurable data entry program for archaeology
Home-page: https://github.com/surf3s/E5
Author: Shannon P. McPherron
Author-email: mcpherron@eva.mpg.de
License: MIT
Project-URL: Bug Tracker, https://github.com/surf3s/E5/issues
Platform: unix
Platform: linux
Platform: osx
Platform: cygwin
Platform: win32
Classifier: Programming Language :: Python :: 3
Classifier: Programming Language :: Python :: 3 :: Only
Classifier: Programming Language :: Python :: 3.8
Classifier: Programming Language :: Python :: 3.9
Classifier: License :: OSI Approved :: MIT License
Classifier: Operating System :: OS Independent
Requires-Python: >=3.8
License-File: LICENSE
Requires-Dist: kivy>=2
Requires-Dist: tinydb>=4
Requires-Dist: plyer>=2
Requires-Dist: pyenchant>=3.2.2
Requires-Dist: appdata>=2.2
Requires-Dist: requests>=2.28.1
Requires-Dist: platformdirs>=3.11.0
Provides-Extra: testing
Requires-Dist: pytest>=6.0; extra == "testing"
Requires-Dist: pytest-cov>=2.0; extra == "testing"
Requires-Dist: mypy>=0.910; extra == "testing"
Requires-Dist: flake8>=3.9; extra == "testing"
Requires-Dist: tox>=3.24; extra == "testing"
